{"code":200,"message":"success","data":{"content":[{"name":"BISHOP社合集","size":0,"is_dir":true,"modified":"2023-04-26T03:47:41Z","sign":"","thumb":"","type":1},{"name":"BouSoft社合集","size":0,"is_dir":true,"modified":"2023-04-26T03:47:41Z","sign":"","thumb":"","type":1},{"name":"Double Soft Cream社3D动画+游戏小合集","size":0,"is_dir":true,"modified":"2023-08-04T02:06:22Z","sign":"","thumb":"","type":1},{"name":"JSK工房","size":0,"is_dir":true,"modified":"2023-04-26T03:47:41Z","sign":"","thumb":"","type":1},{"name":"Marmalade Star 出包王女3D游戏合集","size":0,"is_dir":true,"modified":"2023-04-26T07:43:34Z","sign":"","thumb":"","type":1},{"name":"day系列 (日在校园系列)游戏合集","size":0,"is_dir":true,"modified":"2023-08-08T02:19:22Z","sign":"","thumb":"","type":1},{"name":"illusion社游戏合集 54个","size":0,"is_dir":true,"modified":"2023-08-09T09:59:12Z","sign":"","thumb":"","type":1},{"name":"【PC+安卓+视频】梅麻吕合集","size":0,"is_dir":true,"modified":"2023-04-26T03:47:41Z","sign":"","thumb":"","type":1},{"name":"【PC+安卓】Meet and Fuck系列合集","size":0,"is_dir":true,"modified":"2023-04-26T03:47:41Z","sign":"","thumb":"","type":1},{"name":"【PC+安卓】miel社合集[生肉]","size":0,"is_dir":true,"modified":"2023-04-26T03:47:41Z","sign":"","thumb":"","type":1},{"name":"【PC+安卓】希尔薇整合","size":0,"is_dir":true,"modified":"2023-04-26T03:47:41Z","sign":"","thumb":"","type":1},{"name":"【PC+安卓】纸巾社游戏合集","size":0,"is_dir":true,"modified":"2023-04-26T03:47:41Z","sign":"","thumb":"","type":1},{"name":"【PC+部分KR ONS】12神魔器","size":0,"is_dir":true,"modified":"2023-04-26T03:47:41Z","sign":"","thumb":"","type":1},{"name":"【PC】ANIM社[生肉]","size":0,"is_dir":true,"modified":"2023-04-26T03:47:41Z","sign":"","thumb":"","type":1},{"name":"【PC】Acerola社游戏合集","size":0,"is_dir":true,"modified":"2023-04-26T03:47:41Z","sign":"","thumb":"","type":1},{"name":"【PC】Autobahn社合集","size":0,"is_dir":true,"modified":"2023-05-18T06:15:52Z","sign":"","thumb":"","type":1},{"name":"【PC】BINBIN1919社合集[生肉]","size":0,"is_dir":true,"modified":"2023-04-26T03:47:41Z","sign":"","thumb":"","type":1},{"name":"【PC】Casket社系列","size":0,"is_dir":true,"modified":"2023-04-26T03:47:41Z","sign":"","thumb":"","type":1},{"name":"【PC】CyberStep本社与分社合集","size":0,"is_dir":true,"modified":"2023-06-22T05:24:03Z","sign":"","thumb":"","type":1},{"name":"【PC】Eushully社游戏合集","size":0,"is_dir":true,"modified":"2023-04-26T03:47:41Z","sign":"","thumb":"","type":1},{"name":"【PC】Kagura Games本社与分社合集","size":0,"is_dir":true,"modified":"2023-06-23T16:54:10Z","sign":"","thumb":"","type":1},{"name":"【PC】LiLiM+LiLiM DARKNESS 游戏合集","size":0,"is_dir":true,"modified":"2023-06-25T03:29:35Z","sign":"","thumb":"","type":1},{"name":"【PC】NTRMAN游戏作品小合集","size":0,"is_dir":true,"modified":"2023-04-26T03:47:41Z","sign":"","thumb":"","type":1},{"name":"【PC】ONEONE1本社与分社游戏合集","size":0,"is_dir":true,"modified":"2023-04-26T03:47:41Z","sign":"","thumb":"","type":1},{"name":"【PC】ORCSOFT社游戏合集","size":0,"is_dir":true,"modified":"2023-04-26T03:47:41Z","sign":"","thumb":"","type":1},{"name":"【PC】[SLG]家庭菜園39部合集","size":0,"is_dir":true,"modified":"2023-08-10T03:52:21Z","sign":"","thumb":"","type":1},{"name":"【PC】[わるきゅ～れ]valkria社 2017-2021年合集","size":0,"is_dir":true,"modified":"2023-06-29T05:15:46Z","sign":"","thumb":"","type":1},{"name":"【PC】hibiki社合集","size":0,"is_dir":true,"modified":"2023-04-26T03:47:41Z","sign":"","thumb":"","type":1},{"name":"【PC】key社系列作品","size":0,"is_dir":true,"modified":"2023-04-26T03:47:41Z","sign":"","thumb":"","type":1},{"name":"【PC】more社及分社及mellow社合集","size":0,"is_dir":true,"modified":"2023-06-18T09:14:16Z","sign":"","thumb":"","type":1},{"name":"【PC】sugar star社部分合集","size":0,"is_dir":true,"modified":"2023-04-26T03:47:41Z","sign":"","thumb":"","type":1},{"name":"【PC】【生肉】墳丹吉社作品合集","size":0,"is_dir":true,"modified":"2023-04-26T03:47:41Z","sign":"","thumb":"","type":1},{"name":"【PC】【部分汉化】Lump of Sugar 方糖社合集","size":0,"is_dir":true,"modified":"2023-04-26T03:47:41Z","sign":"","thumb":"","type":1},{"name":"【PC】あれから4年 15部合集","size":0,"is_dir":true,"modified":"2023-06-28T07:21:05Z","sign":"","thumb":"","type":1},{"name":"【PC】エレクトリップ (ErectLip)社合集","size":0,"is_dir":true,"modified":"2023-06-30T04:54:37Z","sign":"","thumb":"","type":1},{"name":"【PC】スタジオ名瀬工作室合集","size":0,"is_dir":true,"modified":"2023-04-26T03:47:41Z","sign":"","thumb":"","type":1},{"name":"【PC】プリックリーアッシュ本社与分社合集","size":0,"is_dir":true,"modified":"2023-05-18T05:59:51Z","sign":"","thumb":"","type":1},{"name":"【PC】中二社全家桶","size":0,"is_dir":true,"modified":"2023-04-26T03:47:41Z","sign":"","thumb":"","type":1},{"name":"【PC】夜羊社全家桶","size":0,"is_dir":true,"modified":"2023-04-26T03:47:41Z","sign":"","thumb":"","type":1},{"name":"【PC】炎孕系列超大合集13部","size":0,"is_dir":true,"modified":"2023-04-26T03:47:41Z","sign":"","thumb":"","type":1},{"name":"【PC】猫拳社合集","size":0,"is_dir":true,"modified":"2023-04-26T03:47:41Z","sign":"","thumb":"","type":1},{"name":"【PC】神乳社28部合集","size":0,"is_dir":true,"modified":"2023-04-26T03:47:41Z","sign":"","thumb":"","type":1},{"name":"【PC】竹子社游戏合集","size":0,"is_dir":true,"modified":"2023-04-26T03:47:41Z","sign":"","thumb":"","type":1},{"name":"【PC】边境社全家桶","size":0,"is_dir":true,"modified":"2023-04-26T03:47:41Z","sign":"","thumb":"","type":1},{"name":"【PC】过激\u0026凌辱\u0026姬辱作品整合","size":0,"is_dir":true,"modified":"2023-04-26T03:47:41Z","sign":"","thumb":"","type":1},{"name":"【PC】音符社全家桶","size":0,"is_dir":true,"modified":"2023-04-26T03:47:41Z","sign":"","thumb":"","type":1},{"name":"【RPG  NTR  PC】Orange Piece（橘子社）合集","size":0,"is_dir":true,"modified":"2023-04-26T03:47:41Z","sign":"","thumb":"","type":1},{"name":"【RPG】幼心君游戏合集","size":0,"is_dir":true,"modified":"2023-06-03T09:23:00Z","sign":"","thumb":"","type":1},{"name":"【游戏+动画+漫画+CG】7thDream社合集","size":0,"is_dir":true,"modified":"2023-04-26T03:47:41Z","sign":"","thumb":"","type":1},{"name":"ヴィンセント社团 24部大合集","size":0,"is_dir":true,"modified":"2023-08-05T03:43:53Z","sign":"","thumb":"","type":1},{"name":"真剣で私に恋しなさい！系列合集","size":0,"is_dir":true,"modified":"2023-06-30T07:09:56Z","sign":"","thumb":"","type":1},{"name":"汉化galgame会社合集","size":0,"is_dir":true,"modified":"2023-08-14T06:12:51.1061878+08:00","sign":"","thumb":"","type":1},{"name":"浮士德galgame游戏合集-1","size":0,"is_dir":true,"modified":"2023-08-13T06:17:51.24388507+08:00","sign":"","thumb":"","type":1},{"name":"浮士德galgame游戏合集-2","size":0,"is_dir":true,"modified":"2023-07-31T00:17:07.182032633+08:00","sign":"","thumb":"","type":1}],"total":54,"readme":"","write":false,"provider":"WebDav"}}