{"code":200,"message":"success","data":{"content":[{"name":"TOKYO天魔冷狐版(开局送作弊器).apk","size":276842997,"is_dir":false,"modified":"2023-04-26T03:49:23Z","sign":"b6fjfgmU5bdn0djxOKh1embFCiNPqfslcRPd9WuW43w=:0","thumb":"","type":0},{"name":"洛顿冷狐版(开局送作弊器).apk","size":183098564,"is_dir":false,"modified":"2023-04-26T03:49:23Z","sign":"_TMp4ILgPKI1CfKnVT_ojcbtHARmhf6-stHAIbScGQg=:0","thumb":"","type":0},{"name":"流亡的召唤姬冷狐版(开局送作弊器).apk","size":173949286,"is_dir":false,"modified":"2023-04-26T03:49:23Z","sign":"XXv_RiO5AayoeF0658YW-85g-8bqtadi81PC1-qj2ro=:0","thumb":"","type":0},{"name":"流放摄政太后之岛冷狐版(开局送作弊器).apk","size":234398247,"is_dir":false,"modified":"2023-04-26T03:49:23Z","sign":"e2WMUCFbLruhygwR8fJ5_mji_IdQ3ZeIiLHGi_HuDgg=:0","thumb":"","type":0},{"name":"流浪少女怜冷狐版(开局送作弊器).apk","size":333364422,"is_dir":false,"modified":"2023-04-26T03:49:23Z","sign":"uGcejnEoIP-o543X9N_0nTyRHxHk5VAWDku27mVVg5U=:0","thumb":"","type":0},{"name":"浪漫世界0.03.apk","size":563318660,"is_dir":false,"modified":"2023-04-26T03:49:23Z","sign":"zR24iUn4-jSEezFt8i_zakhmf5fNl6bnPWEAvhWU2XI=:0","thumb":"","type":0},{"name":"浪漫世界0.55.apk","size":861670105,"is_dir":false,"modified":"2023-04-26T03:49:23Z","sign":"sIMt_PkJFwczQMz0bvilg3mSs2EeKY2zVX7aDIRXqdU=:0","thumb":"","type":0},{"name":"浴室迷宫冷狐双核版(开局送作弊器).apk","size":101132139,"is_dir":false,"modified":"2023-04-26T03:49:23Z","sign":"8hkB4TcoWBeCLs1TZoYxY2O2F8zZWb0YXS0WFhP3xzE=:0","thumb":"","type":0},{"name":"海之孤岛冷狐三核版(开局送作弊器).apk","size":432027109,"is_dir":false,"modified":"2023-04-26T03:49:23Z","sign":"P1Q75qtoMBQBkw62JAzP0NAczhiDaS1c_AHdRAfJGI8=:0","thumb":"","type":0},{"name":"海洋少女冷狐版(开局送作弊器).apk","size":86456432,"is_dir":false,"modified":"2023-04-26T03:49:23Z","sign":"ZKI0yItXKtRV21ScvNuQBqvB31JrYb6bYoxEHAQsQ88=:0","thumb":"","type":0},{"name":"消遣用RPG冷狐版(开局送作弊器).apk","size":291491663,"is_dir":false,"modified":"2023-04-26T03:49:23Z","sign":"IssShT8Ju1cs_cV6mimOOB_wS580noIILinIeZe5c7c=:0","thumb":"","type":0},{"name":"涉谷凛历险记冷狐版(开局送作弊器).apk","size":185872548,"is_dir":false,"modified":"2023-04-26T03:49:23Z","sign":"PHBZ013WdnWXZN3Tvt4fFIntMr30y2CJaNmM6VNGSJA=:0","thumb":"","type":0},{"name":"涩欲迷宫冷狐三核版(开局送作弊器).apk","size":77167698,"is_dir":false,"modified":"2023-04-26T03:49:23Z","sign":"Z_AAGOAIwFqgNp-j03p43xStEdwZZW4xFmCwHsH4Wog=:0","thumb":"","type":0},{"name":"淑女之香2冷狐双核版(开局送作弊器).apk","size":958383018,"is_dir":false,"modified":"2023-04-26T03:49:23Z","sign":"4vN-O9cfUAaNwUUZ14uXzPdyd85cPS3at-m8Zn_QhKs=:0","thumb":"","type":0},{"name":"淑女别墅冷狐三核版(开局送作弊器).apk","size":820585823,"is_dir":false,"modified":"2023-04-26T03:49:23Z","sign":"NrzFVS_68IMfKmGdsZRFYGDqaI1X-9G38cnLDVKwKGI=:0","thumb":"","type":0},{"name":"淑女都市0.6e冷狐版(卧室电脑里有作弊器).apk","size":877991350,"is_dir":false,"modified":"2023-04-26T03:49:23Z","sign":"CHWmZknBa3svn7Bgx5VkWD08JOIYXVFUFWPPL5N7jxw=:0","thumb":"","type":0},{"name":"淡红梅卫士_死之灾厄冷狐三核版开局送作弊器.apk","size":58109333,"is_dir":false,"modified":"2023-04-26T03:49:23Z","sign":"RM3EAikRmdRJawyliIhig1s3_Dip4aMgm6YNXyxkQfc=:0","thumb":"","type":0},{"name":"淫乱的圣骑士.apk","size":311774296,"is_dir":false,"modified":"2023-04-26T03:49:23Z","sign":"LzhWmSwCtE4XW5s2Lszd2puqz4Lc4TAdejeRzld11Eo=:0","thumb":"","type":0},{"name":"淫欲破坏者~ラストブレイカー 汉化版.apk","size":466214706,"is_dir":false,"modified":"2023-04-26T03:49:23Z","sign":"yNRfnXwRe-HbQ3MDizLQZ17E-7YtH6TzvcmHTvBkmAA=:0","thumb":"","type":0},{"name":"淫纹勇者.apk","size":576796861,"is_dir":false,"modified":"2023-04-26T03:49:23Z","sign":"Mw6rOz_O6StvrQMTZOXVk83LKt-pu47a-JM4CjnLE1M=:0","thumb":"","type":0},{"name":"淫魔与失落的圣杯.apk","size":505007953,"is_dir":false,"modified":"2023-04-26T03:49:23Z","sign":"-gZXgy8Yx9aDSgUSPE-tMFRkc5XcAbaBy9GPrP3FK7U=:0","thumb":"","type":0},{"name":"淫魔大乱斗.apk","size":160079259,"is_dir":false,"modified":"2023-04-26T03:49:23Z","sign":"57nwnnc0fHPDIVuajRt1xKggWxofWQanW013PujSDDw=:0","thumb":"","type":0},{"name":"淫魔的盛宴与圣女的法悦 Succubus × Saint.apk","size":352487328,"is_dir":false,"modified":"2023-04-26T03:49:23Z","sign":"MNMhGAuh9vyt_2EZNIUAY-WcS1LjT2ijuIEVkH67e8k=:0","thumb":"","type":0},{"name":"深水少女冷狐版(开局送作弊器).apk","size":165986911,"is_dir":false,"modified":"2023-04-26T03:49:23Z","sign":"StomoErXADO6sR9tPTN_j50z5i2opd6If-XvErEMTIE=:0","thumb":"","type":0},{"name":"深渊-异世界的少女冷狐版(开局送作弊器).apk","size":149327222,"is_dir":false,"modified":"2023-04-26T03:49:23Z","sign":"T6d-ML0LsQ04mcLom7nEimq4kVcZW16Vgk8CzgGSrMQ=:0","thumb":"","type":0},{"name":"深渊探索者冷狐双核版(开局送作弊器).apk","size":322649247,"is_dir":false,"modified":"2023-04-26T03:49:23Z","sign":"cVznnEZ3BvRvjHkt5HpWJhBapPBofp_9la5Ywp8A1t0=:0","thumb":"","type":0},{"name":"深渊洞穴冷狐三核版(开局送作弊器).apk","size":53729174,"is_dir":false,"modified":"2023-04-26T03:49:23Z","sign":"qDGothSIZ-ZhJ2tMyLFx34rKmr-x82sSzJ1kTxUbaCM=:0","thumb":"","type":0},{"name":"深渊的探索者~深淵の探索者.apk","size":852223407,"is_dir":false,"modified":"2023-04-26T03:49:23Z","sign":"OiNppWLE2SIma5zu437L7TTiNeIVFQU3uTKJZLpAOio=:0","thumb":"","type":0},{"name":"深红之狱的女剑士蒂娜Tina_Swordswoman_of_the_Scarlet_Prison汉化版.apk","size":1295244376,"is_dir":false,"modified":"2023-04-26T03:49:23Z","sign":"iLqb17fTjdyty5vXCWTX-jcP17TGCgynesoEIVR6Tts=:0","thumb":"","type":0},{"name":"深红之狱的女剑士蒂娜冷狐三核版开局送作弊器.apk","size":425210280,"is_dir":false,"modified":"2023-04-26T03:49:23Z","sign":"SMtNnk4n6q8bB1YSPhLj8iUDLdojLEox0ukyeV_Qcro=:0","thumb":"","type":0},{"name":"清秀学园冷狐版(开局送作弊器).apk","size":145163349,"is_dir":false,"modified":"2023-04-26T03:49:23Z","sign":"ktJq1Q7qp_qdKORY3N4bC_rh7q-tVKOqJmdVyve5D8M=:0","thumb":"","type":0},{"name":"清纯JK的Y乱化计划冷狐版(开局送作弊器).apk","size":193466967,"is_dir":false,"modified":"2023-04-26T03:49:23Z","sign":"bufJqgutuznxmqz5-xt7gMWl9IHcaQEeg7CH79ESX4Q=:0","thumb":"","type":0},{"name":"清纯系人7的艾薇企划挑战冷狐三核版开局送作弊器.apk","size":34435781,"is_dir":false,"modified":"2023-04-26T03:49:23Z","sign":"E6-c7zaUYtX-cQyIaEUJsQv4F3GFc-6W79IYELIShIY=:0","thumb":"","type":0},{"name":"清纯系人妻的AV企划挑战！背负债务的已婚妇女_瞒着丈夫的AV演出！.apk","size":100923924,"is_dir":false,"modified":"2023-04-26T03:49:23Z","sign":"SJLLEUdGfdqe9C837uFBP9_VV71ZFQJTj643aX0vp6w=:0","thumb":"","type":0},{"name":"温尔莎的炼精工坊.apk","size":291066865,"is_dir":false,"modified":"2023-04-26T03:49:23Z","sign":"6q6mR7rciL9tqTvgYOU_uWFlvuSY7zVaS7e7VeQ3Ja0=:0","thumb":"","type":0},{"name":"温泉欲念挑战-桃子冷狐三核版(开局送作弊器).apk","size":50814897,"is_dir":false,"modified":"2023-04-26T03:49:23Z","sign":"wT8gJWEzBaxpM88c38UpfrniPdnVpoOhI5RFOwgHtsw=:0","thumb":"","type":0},{"name":"温泉痴女 性挑战①桃子篇.apk","size":228419457,"is_dir":false,"modified":"2023-04-26T03:49:23Z","sign":"hOswJszNysvoEJiFldDFaqyDDFYYiVN0_GjK0MYpA4k=:0","thumb":"","type":0},{"name":"游戏厅的少女冷狐版(开局送作弊器).apk","size":174867234,"is_dir":false,"modified":"2023-04-26T03:49:23Z","sign":"2LxXOqDVukonXooGnIczm-CHDBmWpwYXpI3C11dn76I=:0","thumb":"","type":0},{"name":"游戏键盘.apk","size":313957,"is_dir":false,"modified":"2023-04-26T03:49:23Z","sign":"eiOVUtfsdKizC2ku5uCVlvnG-gSDw92Y7M0Ot6QB0po=:0","thumb":"","type":0},{"name":"漂亮的大姐姐拷問敏感棒冷狐版按A启动作弊器.apk","size":168270713,"is_dir":false,"modified":"2023-04-26T03:49:23Z","sign":"rWxan3nplPfA_yNjq-rnR0IDO7MrdRxpy6h4Dc2Wp7M=:0","thumb":"","type":0},{"name":"演员~My Girlfriend.apk","size":655812547,"is_dir":false,"modified":"2023-04-26T03:49:23Z","sign":"ravVa6HwjglnE8U2BzyW6YYdycbd1F4V12GaA8GvKQM=:0","thumb":"","type":0},{"name":"漠银之音-落难女君冷狐三核版(开局送作弊器).apk","size":97342304,"is_dir":false,"modified":"2023-04-26T03:49:23Z","sign":"bQk6Swi9mIkDchkAVb13fFUnDsnJo8lSKVciSu3t4RM=:0","thumb":"","type":0},{"name":"潘多拉之箱冷狐版(开局送作弊器).apk","size":187672089,"is_dir":false,"modified":"2023-04-26T03:49:23Z","sign":"1jEBHXQ7AnymKLsKrAcWjoAWHCpyURJrbF1QQnY9Gcg=:0","thumb":"","type":0},{"name":"潘多拉历险记~パンダラクエスト1.03汉化版.apk","size":950040931,"is_dir":false,"modified":"2023-04-26T03:49:23Z","sign":"8nj_231yZrwhCyHYtVSBUYYXylUzBz82W2aSHekcyD0=:0","thumb":"","type":0},{"name":"潘多拉历险记冷狐三核版(开局送作弊器).apk","size":117672998,"is_dir":false,"modified":"2023-04-26T03:49:23Z","sign":"Ud4HQjeq9GYzXdCYx9EwnD-IzMj_llDMTVu8XoKfN14=:0","thumb":"","type":0},{"name":"潘多拉的辞令冷狐三核版(虚拟键盘带作弊器).apk","size":177836308,"is_dir":false,"modified":"2023-04-26T03:49:23Z","sign":"4OTnl48SYHsYNIcqGoQK1Ux0LGX0zSb6llKMd3wKs-8=:0","thumb":"","type":0},{"name":"潜入奸魔冷狐版(开局送作弊器).apk","size":182360000,"is_dir":false,"modified":"2023-04-26T03:49:23Z","sign":"RpxEZU62d5AtgcelxeA5MnF8xoJCbqToPyaXkLhnH8o=:0","thumb":"","type":0},{"name":"潜入少女希尔.apk","size":210691591,"is_dir":false,"modified":"2023-04-26T03:49:23Z","sign":"8baN2FE9n1quJhdpgA8jHesrx_aenNp8lmBZHkuD4BU=:0","thumb":"","type":0},{"name":"潜入少女希尔冷狐双核版(开局送作弊器).apk","size":43165330,"is_dir":false,"modified":"2023-04-26T03:49:23Z","sign":"BHVWk3yqzQfP-718OAL1ngxLMa0YlQjhpQc02lbhFtQ=:0","thumb":"","type":0},{"name":"潜入搜查官冷狐版(开局送作弊器).apk","size":185214277,"is_dir":false,"modified":"2023-04-26T03:49:23Z","sign":"kGPV9gudQ6KKXOptMrRLN92-TKVCZlCvbgauilidRtM=:0","thumb":"","type":0},{"name":"潜入特工玛丽娜冷狐双核版(开局送作弊器).apk","size":157138418,"is_dir":false,"modified":"2023-04-26T03:49:23Z","sign":"wl5Wy90bulXFVTfZZJGJb41hjv7TBpeqBoPFh_Ze6VU=:0","thumb":"","type":0},{"name":"激情小镇2.32冷狐三核版(开局送作弊器).apk","size":268946010,"is_dir":false,"modified":"2023-04-26T03:49:23Z","sign":"jTp_mAwLzOmT8_IJg8ZKTgEGNDZkBZ4hit2L5o2uh4M=:0","thumb":"","type":0},{"name":"激情燃烧的岁月0.35.apk","size":880933185,"is_dir":false,"modified":"2023-04-26T03:49:23Z","sign":"hA8Fp4WchcglE18Epa-_sA9iZc9rvdZ2Mu55J5qTysk=:0","thumb":"","type":0},{"name":"激情燃烧的岁月8.01冷狐版(便利店ATM作弊).apk","size":1066895661,"is_dir":false,"modified":"2023-04-26T03:49:23Z","sign":"2pFdfpH-4xKNxQ_gzM7fHlTAeVPrEW1z6OnyAQ0FQwU=:0","thumb":"","type":0},{"name":"激情跳动冷狐版(开局送作弊器).apk","size":137902095,"is_dir":false,"modified":"2023-04-26T03:49:23Z","sign":"gPuPYOjGSVWBtL0fC0ZMnwBBDyfA-iYPqi3-6iYRCoY=:0","thumb":"","type":0},{"name":"火众之忍冷狐三核版(开局送作弊器).apk","size":165474445,"is_dir":false,"modified":"2023-04-26T03:49:23Z","sign":"ff86P549L0Dt5YEiIOaXtyhr7ibouR4VaGxi5CL30uM=:0","thumb":"","type":0},{"name":"火枪手蒂娜冷狐三核版(开局送作弊器).apk","size":118457704,"is_dir":false,"modified":"2023-04-26T03:49:23Z","sign":"xFRTPChZPBpwbKuBzBvYRPQADTPHSbDGVyFNLWJ5-X0=:0","thumb":"","type":0},{"name":"火焰纹章1冷狐三核版(开局送作弊器).apk","size":40700070,"is_dir":false,"modified":"2023-04-26T03:49:23Z","sign":"Nuu2qSe-9yqzVCkWe-8nDGtCvq3MFY3RcqZQktLfIFg=:0","thumb":"","type":0},{"name":"火焰纹章2冷狐三核版(开局送作弊器).apk","size":182687743,"is_dir":false,"modified":"2023-04-26T03:49:23Z","sign":"jV9WYbrH5UlN7hCiYO4pDzmKssPPX8370bQVAMDbX9w=:0","thumb":"","type":0},{"name":"灰姑娘的换装冷狐三核版(开局送作弊器).apk","size":110250850,"is_dir":false,"modified":"2023-04-26T03:49:23Z","sign":"55f7oiiatx1dqsLKsOlw85nr_Yqi7CvWHFgCWOq8aYE=:0","thumb":"","type":0},{"name":"灵魂拯救者.apk","size":413936130,"is_dir":false,"modified":"2023-04-26T03:49:23Z","sign":"mGHHi_88Wt7Z6j5uiyuKBKVXAApolVnt3DVFFP1Q6bc=:0","thumb":"","type":0},{"name":"灵魂拯救者冷狐双核版(开局送作弊器).apk","size":102491298,"is_dir":false,"modified":"2023-04-26T03:49:23Z","sign":"Vc6sIkaQL7CqmXB6Fyl47BICBu4EjeXbgT58L2-FHqQ=:0","thumb":"","type":0},{"name":"灼炎骑士1.1冷狐版(开局送作弊器).apk","size":213505782,"is_dir":false,"modified":"2023-04-26T03:49:23Z","sign":"JnFS3FbBqdywJUsMUSfdOLDOhkdZdqLL6Q-dCi16MeQ=:0","thumb":"","type":0},{"name":"灾难实验室冷狐版(开局送作弊器).apk","size":227426057,"is_dir":false,"modified":"2023-04-26T03:49:23Z","sign":"4edXlvx1QY9IKGpcYZ0SAekChTaOrAxMB2LQxyyG7wQ=:0","thumb":"","type":0},{"name":"炎之孕!超工口超能催眠学院.apk","size":1348246222,"is_dir":false,"modified":"2023-04-26T03:49:23Z","sign":"vWxhsfYIW4wpHowIMKhwD6_iY-tDt1o-TJ8SE1gN0qg=:0","thumb":"","type":0},{"name":"炎之魔女与土之随者冷狐版(开局送作弊器).apk","size":216780839,"is_dir":false,"modified":"2023-04-26T03:49:23Z","sign":"5WtblXXJ5z3LCsOIJTl8-zS0pNOCbta7uU1XKtrqAY8=:0","thumb":"","type":0},{"name":"炼狱姬安玛夺回炼狱城作战计划冷狐版开局送作弊器.apk","size":181252537,"is_dir":false,"modified":"2023-04-26T03:49:23Z","sign":"mH8iKAZhDw4eGE8FRD7LMPaP46pJ6ng6IIlFiPNy5PE=:0","thumb":"","type":0},{"name":"炼精术师冷狐三核版(虚拟键盘带作弊器).apk","size":541839893,"is_dir":false,"modified":"2023-04-26T03:49:23Z","sign":"V37rx6NcbfBYUoTjbuuZBxiiw3R9MKA-sVWGdXzOveo=:0","thumb":"","type":0},{"name":"炼金工坊冷狐版(开局送作弊器).apk","size":47233455,"is_dir":false,"modified":"2023-04-26T03:49:23Z","sign":"NcQuSCCmuW1A2uU5bJdYKEZU40WQKEWS_7SbStpcTwQ=:0","thumb":"","type":0},{"name":"炼金术师的异世界之旅冷狐三核版开局送作弊器.apk","size":45296242,"is_dir":false,"modified":"2023-04-26T03:49:23Z","sign":"g2K38E1TdWTJ_4Ou7LBx0tNT28ixLhTdLPPV5bfUFM0=:0","thumb":"","type":0},{"name":"炼金术的性反转冷狐版(开局送作弊器).apk","size":79160301,"is_dir":false,"modified":"2023-04-26T03:49:23Z","sign":"2pVCY7WTzvZfs9YKQk1jqIGu6BSWrhLoDv9rNW3Ey_U=:0","thumb":"","type":0},{"name":"炼铜小游戏.apk","size":33695480,"is_dir":false,"modified":"2023-04-26T03:49:23Z","sign":"abhn7ff1W0q0z2eEg7UQv-dc-EZriJmyODiy7SYrRFs=:0","thumb":"","type":0},{"name":"热血硬派冷狐三核版(开局送作弊器).apk","size":1425519806,"is_dir":false,"modified":"2023-04-26T03:49:23Z","sign":"vLK52ktjhLE67euVPgf2rpLjmqO-ysnbZGUuk6MPtzI=:0","thumb":"","type":0},{"name":"焰发的玛琪娜冷狐三核版(开局送作弊器).apk","size":207053631,"is_dir":false,"modified":"2023-04-26T03:49:23Z","sign":"YFX0R0RzzFIM_AT1AEtmvYBk-uM9_bhtFZwRJ9z_3RI=:0","thumb":"","type":0},{"name":"然而姬骑士步履不停冷狐版(按A启动作弊器).apk","size":144314955,"is_dir":false,"modified":"2023-04-26T03:49:23Z","sign":"NIj4G5fiIQd5cJMS2l6LoDsquzSEinBNWw8ej2h7IQs=:0","thumb":"","type":0},{"name":"熟女传说1.2.apk","size":981594298,"is_dir":false,"modified":"2023-04-26T03:49:23Z","sign":"rIxvJRpsIvNiFiPBgYLdMLjBtYPz0_jXhjnqzRkdkis=:0","thumb":"","type":0},{"name":"爆R人7的YD派对冷狐三核版(开局送作弊器).apk","size":112995214,"is_dir":false,"modified":"2023-04-26T03:49:23Z","sign":"aRABIpKs2GdY6KbkXge2QMfQHe-oOtZn25QMchV6epw=:0","thumb":"","type":0},{"name":"爆R公主骑士冷狐三核版(开局送作弊器).apk","size":95080723,"is_dir":false,"modified":"2023-04-26T03:49:23Z","sign":"wd8kfuK0F68V6FekInkwcDDejfozYJz3EPlVbMGPuvM=:0","thumb":"","type":0},{"name":"爆乳精靈妻和早洩君~催眠寢取偷窺記錄.apk","size":957768168,"is_dir":false,"modified":"2023-04-26T03:49:23Z","sign":"Dlk_PTtbmp32D1KYuA0Jy-rnGJy6k3AtWzDiSSOcICs=:0","thumb":"","type":0},{"name":"爆乳老师DX冷狐三核版(开局送作弊器).apk","size":53480178,"is_dir":false,"modified":"2023-04-26T03:49:23Z","sign":"Q4P-Rw_hNnXtyoK94s0g02AhN4tR9b5Iuvo-jEPIdv8=:0","thumb":"","type":0},{"name":"爆灾雷钢~雷王号 官方中文无修正 1.02版.apk","size":500673068,"is_dir":false,"modified":"2023-04-26T03:49:23Z","sign":"tSHDCOEe7A55bZQdW-iBn-DmNythB2EhLcXuWnB6RXU=:0","thumb":"","type":0},{"name":"爆炎雷钢佑狮龙冷狐三核版(开局送作弊器).apk","size":117836099,"is_dir":false,"modified":"2023-04-26T03:49:23Z","sign":"tfkPNdXzq8_u3RotMw5qiYKKRVJ_seC9zyw-H-MFX84=:0","thumb":"","type":0},{"name":"爆炎雷钢佑狮龙冷狐双核版(开局送作弊器).apk","size":116660578,"is_dir":false,"modified":"2023-04-26T03:49:23Z","sign":"WCL008u7rwj4YXLWIOGN2XejitSmD_fKXvddxj66oUk=:0","thumb":"","type":0},{"name":"爱丽丝和神秘的少女们冷狐三核版开局送作弊器.apk","size":634187838,"is_dir":false,"modified":"2023-04-26T03:49:23Z","sign":"FsOHgRByCjkb5sI7ZuM_ozqTHk5x8OGDbuLDDaXfh68=:0","thumb":"","type":0},{"name":"爱丽丝的追求之路冷狐版(开局送作弊器).apk","size":202326810,"is_dir":false,"modified":"2023-04-26T03:49:23Z","sign":"kkVf83uAe740uBcQ7pxsKnrgdaXMigNyq03gkqwmHQo=:0","thumb":"","type":0},{"name":"爱丽丝酱-被玩坏的世界冷狐版(开局送作弊器).apk","size":87539277,"is_dir":false,"modified":"2023-04-26T03:49:23Z","sign":"MvCJ51OczDgVhbmg6jvmwWjYR5-2L6hWFhVufk4KWvY=:0","thumb":"","type":0},{"name":"爱之狐狸冷狐三核版(开局送作弊器).apk","size":25888421,"is_dir":false,"modified":"2023-04-26T03:49:23Z","sign":"BlCJakJLgsnGYB0Hz62z3vrHRF1yLJI6085tlvp2NO8=:0","thumb":"","type":0},{"name":"爱之莉莉丝冷狐三核版(开局送作弊器).apk","size":28746850,"is_dir":false,"modified":"2023-04-26T03:49:23Z","sign":"96gG4FqaTo1WWLtJy8fdDm1IE3T6zIuzyttISYnsknc=:0","thumb":"","type":0},{"name":"爱之萝莉冷狐三核版(开局送作弊器).apk","size":29323331,"is_dir":false,"modified":"2023-04-26T03:49:23Z","sign":"lCkzasT5fyv0B1DIddPAgJB1DDJsuh7BlgpS3nppgco=:0","thumb":"","type":0},{"name":"爱妻日记.apk","size":548427954,"is_dir":false,"modified":"2023-04-26T03:49:23Z","sign":"0YB6cLBv_TRtm0819IzqX44n7hx88DUoj_XID2kYWMo=:0","thumb":"","type":0},{"name":"爱情药剂冷狐版(开局改好感全CG解锁).apk","size":340708400,"is_dir":false,"modified":"2023-04-26T03:49:23Z","sign":"jqyg7lfqGdvzJcC9ND6_rC0-TBvilhggTKm5YsxEG-M=:0","thumb":"","type":0},{"name":"爱惜0.3冷狐三核版(开局送作弊器).apk","size":177922348,"is_dir":false,"modified":"2023-04-26T03:49:23Z","sign":"z9e7TQH6aBcvNHcJVIQ4I_wUIP6EyLO3AL_kVKpne8w=:0","thumb":"","type":0},{"name":"爱抖露少女育成计划冷狐版(开局送作弊器).apk","size":136084736,"is_dir":false,"modified":"2023-04-26T03:49:23Z","sign":"CccW5gVgFs-YKOo1s7z8eVxO-4vhcHBkM4XA7DJl0xI=:0","thumb":"","type":0},{"name":"爱抖露脱出冒险冷狐版(开局送作弊器).apk","size":130078545,"is_dir":false,"modified":"2023-04-26T03:49:23Z","sign":"nLLvRkRzqs8HtLGcyTtAJN4ftREUyXYQgYu0Exdkh_k=:0","thumb":"","type":0},{"name":"爱衣的花园冷狐双核版(开局送作弊器).apk","size":84078651,"is_dir":false,"modified":"2023-04-26T03:49:23Z","sign":"JUoDug55BF3TO2L2J26oxxjxh5Z7OdHudFaLifnQvoI=:0","thumb":"","type":0},{"name":"爱露莎的谋财冒险冷狐版(开局送作弊器).apk","size":122575123,"is_dir":false,"modified":"2023-04-26T03:49:23Z","sign":"EM5eOqxCjvtqAvYnh00tvVYKfk3MVGm2xy7Zokl1s9Q=:0","thumb":"","type":0},{"name":"父亲与彩子风花雪月的故事.apk","size":289733281,"is_dir":false,"modified":"2023-04-26T03:49:23Z","sign":"e20cjqBz-MQTjyqOvuacVR5FUe4E-pRshda313qXDxM=:0","thumb":"","type":0},{"name":"父女岛1冷狐版(开局看CG).apk","size":1818895416,"is_dir":false,"modified":"2023-04-26T03:49:23Z","sign":"yPhXrCcDoIxJSXOvw8CKeuO5kHU03LBhf5u_68AzZMQ=:0","thumb":"","type":0},{"name":"牛奶牧场冷狐三核版(开局送作弊器).apk","size":200348190,"is_dir":false,"modified":"2023-04-26T03:49:23Z","sign":"2srTb_IQfw6LusWtl7tra1itjMhQbCNHSjGZlX4avSg=:0","thumb":"","type":0},{"name":"特务退魔忍1.0冷狐版(开局送作弊器).apk","size":230466207,"is_dir":false,"modified":"2023-04-26T03:49:23Z","sign":"vCrb4rEU3P-vgy4OU4ww8Rz91vNeaCaGcvavxz3L6vE=:0","thumb":"","type":0}],"total":100,"readme":"","write":false,"provider":"WebDav"}}