{"code":200,"message":"success","data":{"content":[{"name":"APK","size":0,"is_dir":true,"modified":"2023-04-23T08:33:30Z","sign":"","thumb":"","type":1},{"name":"KRKR","size":0,"is_dir":true,"modified":"2023-04-23T08:33:30Z","sign":"","thumb":"","type":1},{"name":"ONS","size":0,"is_dir":true,"modified":"2023-04-23T08:33:30Z","sign":"","thumb":"","type":1},{"name":"【安卓SLG汉化】美少女偶像练习生.7z","size":461149038,"is_dir":false,"modified":"2023-04-23T08:33:30Z","sign":"XOhox8txn_VAYGMab9iNbySkeu0u-KIYVJkosD4EfKs=:0","thumb":"","type":0},{"name":"【安卓】前辈和不可思议的迷宫.7z","size":210974449,"is_dir":false,"modified":"2023-04-23T08:33:30Z","sign":"6uqlE2jgb8lB9934Mc_snqMbo3KCTICpz9PJrI8LzJM=:0","thumb":"","type":0},{"name":"【安卓】状态异常～寄生虫编.7z","size":724040978,"is_dir":false,"modified":"2023-04-23T08:33:30Z","sign":"4U6-HF8cNe31dJrlVJE7BVKRvUv_SA7WRK--vgmtIYo=:0","thumb":"","type":0},{"name":"【安卓】禁忌之岛-丧尸起源ver3.5.7z","size":1260149314,"is_dir":false,"modified":"2023-04-23T08:33:30Z","sign":"K7KLK0ms7h6UUxO7t6UJriwYb2EAFtoMEg_KBVk15YA=:0","thumb":"","type":0},{"name":"安卓 纸巾盒 八部合集 (ティッシュはこ).rar","size":361576478,"is_dir":false,"modified":"2023-04-23T08:33:30Z","sign":"1TzFRE8w4iHTDJuhM6DcJ8MqK_37aJD4X-CzJs8nyeA=:0","thumb":"","type":0},{"name":"安卓`亡国公主爱丽丝.7z","size":1003649493,"is_dir":false,"modified":"2023-04-23T08:33:30Z","sign":"6_aWXhWI0dFMSHYJo-vk2Lr9pRem58ECWaK_y9-vzEM=:0","thumb":"","type":0}],"total":9,"readme":"# 说明\n### 夏风交流群：[夏风讨论组](https://t.me/xiafengforever)\n\n**按顺序依次尝试**\n\n - **一级解压密码：**\n\t - `半夏`\n\t - `莱茵`\n\t - `LaiYin `\n\t - `ed2k `\n\t - `三次郎`\n\t - `终点`\n\t - `91acg.xyz  `\n\t - `ACGKNOW  `\n\t - `www.acgfbw.com  `\n\t - `www.acgfabu.com  `\n\t - `www.agbbc.com  `\n\t - `www.acgfabu.com  `\n\t - `天才小熊an  `\n\t - `⑨**  `\n\t\n\n\n\n\n\n\n\n\n","write":false,"provider":"WebDav"}}